RenameUtility/__init__.py
RenameUtility-0.1.dist-info/LICENSE.txt
RenameUtility-0.1.dist-info/METADATA
RenameUtility-0.1.dist-info/WHEEL
RenameUtility-0.1.dist-info/top_level.txt
RenameUtility-0.1.dist-info/RECORD
