Metadata-Version: 2.1
Name: RenameUtility
Version: 0.1
Summary: This is to rename all files to desired extensions and also rename extensions inside the file
Home-page: UNKNOWN
Author: NikhilaVN
Author-email: vnaganikhila@dovercorp.com
License: UNKNOWN
Platform: UNKNOWN
Classifier: Programming Language :: Python :: 3
Classifier: License :: OSI Approved :: MIT License
Classifier: Operating System :: OS Independent
